odoo10_addon_partner_contact_weight-10.0.1.0.0-py2.7-nspkg.pth
odoo10_addon_partner_contact_weight-10.0.1.0.0.dist-info/top_level.txt
odoo10_addon_partner_contact_weight-10.0.1.0.0.dist-info/WHEEL
odoo10_addon_partner_contact_weight-10.0.1.0.0.dist-info/RECORD
odoo10_addon_partner_contact_weight-10.0.1.0.0.dist-info/metadata.json
odoo10_addon_partner_contact_weight-10.0.1.0.0.dist-info/DESCRIPTION.rst
odoo10_addon_partner_contact_weight-10.0.1.0.0.dist-info/METADATA
odoo10_addon_partner_contact_weight-10.0.1.0.0.dist-info/namespace_packages.txt
odoo/addons/partner_contact_weight/__manifest__.py
odoo/addons/partner_contact_weight/__init__.py
odoo/addons/partner_contact_weight/README.rst
odoo/addons/partner_contact_weight/models/res_partner.py
odoo/addons/partner_contact_weight/models/__init__.py
odoo/addons/partner_contact_weight/i18n/ja.po
odoo/addons/partner_contact_weight/i18n/lv.po
odoo/addons/partner_contact_weight/i18n/zh_CN.po
odoo/addons/partner_contact_weight/i18n/nb_NO.po
odoo/addons/partner_contact_weight/i18n/tr_TR.po
odoo/addons/partner_contact_weight/i18n/ru.po
odoo/addons/partner_contact_weight/i18n/pt.po
odoo/addons/partner_contact_weight/i18n/fr_CH.po
odoo/addons/partner_contact_weight/i18n/it.po
odoo/addons/partner_contact_weight/i18n/es.po
odoo/addons/partner_contact_weight/i18n/nl_BE.po
odoo/addons/partner_contact_weight/i18n/ar.po
odoo/addons/partner_contact_weight/i18n/lt.po
odoo/addons/partner_contact_weight/i18n/ro.po
odoo/addons/partner_contact_weight/i18n/tr.po
odoo/addons/partner_contact_weight/i18n/mk.po
odoo/addons/partner_contact_weight/i18n/hr.po
odoo/addons/partner_contact_weight/i18n/bg.po
odoo/addons/partner_contact_weight/i18n/es_EC.po
odoo/addons/partner_contact_weight/i18n/zh_TW.po
odoo/addons/partner_contact_weight/i18n/hu.po
odoo/addons/partner_contact_weight/i18n/fr_CA.po
odoo/addons/partner_contact_weight/i18n/gl.po
odoo/addons/partner_contact_weight/i18n/ca.po
odoo/addons/partner_contact_weight/i18n/es_CR.po
odoo/addons/partner_contact_weight/i18n/sl.po
odoo/addons/partner_contact_weight/i18n/sr@latin.po
odoo/addons/partner_contact_weight/i18n/th.po
odoo/addons/partner_contact_weight/i18n/cs.po
odoo/addons/partner_contact_weight/i18n/pt_PT.po
odoo/addons/partner_contact_weight/i18n/eu.po
odoo/addons/partner_contact_weight/i18n/nb.po
odoo/addons/partner_contact_weight/i18n/da.po
odoo/addons/partner_contact_weight/i18n/et.po
